dora_utils/dataclasses.py
dora_utils/node.py
dora_utils/examples/chatter/listener.py
dora_utils/examples/chatter/talker.py
dora_utils/launch/_launch_node.py
dora_utils/launch/run.py
dora_utils-0.1.1.dist-info/licenses/LICENSE
dora_utils-0.1.1.dist-info/METADATA
dora_utils-0.1.1.dist-info/WHEEL
dora_utils-0.1.1.dist-info/top_level.txt
dora_utils-0.1.1.dist-info/RECORD
