Metadata-Version: 2.4
Name: dora-utils
Version: 0.1.1
Author-email: Preston Culbertson <pdc79@cornell.edu>, Albert Li <alberthli@caltech.edu>
License: MIT License
Classifier: Programming Language :: Python :: 3
Classifier: License :: OSI Approved :: MIT License
Classifier: Operating System :: OS Independent
Requires-Python: >=3.10
License-File: LICENSE
Requires-Dist: dacite
Requires-Dist: dora-rs-cli
Requires-Dist: hydra-core
Requires-Dist: numpy
Requires-Dist: pyarrow
Provides-Extra: dev
Requires-Dist: pre-commit>=4.1.0; extra == "dev"
Dynamic: license-file
